LICENSE.txt
MANIFEST.in
requirements.txt
setup.cfg
setup.py
lrutilities.egg-info/PKG-INFO
lrutilities.egg-info/SOURCES.txt
lrutilities.egg-info/dependency_links.txt
lrutilities.egg-info/not-zip-safe
lrutilities.egg-info/requires.txt
lrutilities.egg-info/top_level.txt
lrutils/__init__.py
lrutils/address/__init__.py
lrutils/address/address_utils.py
lrutils/audit/__init__.py
lrutils/password/__init__.py
lrutils/password/password_utils.py
lrutils/templatefilters/__init__.py
lrutils/templatefilters/template_filters.py