Metadata-Version: 1.1
Name: lrutilities
Version: 0.1.2
Summary: Utilities for LR Flask apps
Home-page: https://github.com/LandRegistry/lr-utils
Author: Land Registry
Author-email: paul.trelease@digital.landregistry.gov.uk
License: MIT
Download-URL: https://pypi.python.org/packages/2.7/l/lrutilities/lrutilities-0.1.2.tar.gz
Platform: any
Classifier: Development Status :: 3 - Alpha
Classifier: Environment :: Web Environment
Classifier: Programming Language :: Python :: 2.7
